hn_ui/__init__.py
hn_ui/constants.py
hn_ui/helpers.py
hn_ui/main.py
hn_ui-0.1.1.dist-info/METADATA
hn_ui-0.1.1.dist-info/WHEEL
hn_ui-0.1.1.dist-info/entry_points.txt
hn_ui-0.1.1.dist-info/top_level.txt
hn_ui-0.1.1.dist-info/RECORD
