Metadata-Version: 2.4
Name: hn-ui
Version: 0.1.1
Summary: A terminal-based Hacker News reader that displays stories in a beautiful table format.
Requires-Python: >=3.12
Requires-Dist: requests>=2.32.4
Requires-Dist: rich>=14.0.0
